tlo/__init__.py
tlo/tl_config.py
tlo/tl_config_parser.py
tlo/tl_core.py
tlo/tl_simple_parser.py
tlo-1.0.1.dist-info/LICENSE
tlo-1.0.1.dist-info/WHEEL
tlo-1.0.1.dist-info/METADATA
tlo-1.0.1.dist-info/RECORD
