Metadata-Version: 2.1
Name: tlo
Version: 1.0.1
Summary: Reader of binary serialized Type Language Schema
Home-page: https://github.com/MarshalX/tlo
License: MIT
Keywords: library,mtproto,parser,python,schema,tdlib,telegram,telegram-api,tl,tl-parser,tl-schema,tlo,tlo-reader,type-language
Author: Il'ya Semyonov
Author-email: ilya@marshal.dev
Requires-Python: >=3.6,<4.0
Classifier: Development Status :: 5 - Production/Stable
Classifier: Intended Audience :: Developers
Classifier: License :: OSI Approved :: MIT License
Classifier: Natural Language :: English
Classifier: Operating System :: OS Independent
Classifier: Programming Language :: Python
Classifier: Programming Language :: Python :: 3
Classifier: Programming Language :: Python :: 3 :: Only
Classifier: Programming Language :: Python :: 3.6
Classifier: Programming Language :: Python :: 3.7
Classifier: Programming Language :: Python :: 3.8
Classifier: Programming Language :: Python :: 3.9
Classifier: Topic :: Software Development
Classifier: Topic :: Software Development :: Libraries :: Python Modules
Classifier: Topic :: Software Development :: Pre-processors
Project-URL: Author, https://github.com/MarshalX
Project-URL: Repository, https://github.com/MarshalX/tlo
